companies_house_api_client.py
companies_house_api_client-0.0.3.dist-info/LICENCE
companies_house_api_client-0.0.3.dist-info/METADATA
companies_house_api_client-0.0.3.dist-info/WHEEL
companies_house_api_client-0.0.3.dist-info/top_level.txt
companies_house_api_client-0.0.3.dist-info/RECORD
