Metadata-Version: 2.1
Name: companies-house-api-client
Version: 0.0.3
Summary: Simple python wrapper for Companies House API
Home-page: UNKNOWN
Author: Ugurcan Akpulat
License: UNKNOWN
Platform: UNKNOWN
Classifier: Programming Language :: Python :: 3
Classifier: License :: OSI Approved :: MIT License
Classifier: Operating System :: OS Independent
Requires-Python: >=3.6
Requires-Dist: requests
Requires-Dist: python-dotenv
